{
    "objective": "Build runtime capability: self_validation :: validation",
    "result": {
        "success": true,
        "objective": "Build runtime capability: self_validation :: validation",
        "started": "2026-05-20T06:21:30.670046+00:00",
        "completed": "2026-05-20T06:21:30.670046+00:00",
        "error": null,
        "traceback": null,
        "result": {
            "status": "executed",
            "objective": "Build runtime capability: self_validation :: validation"
        }
    }
}